mcp_server.py
iflow_mcp_couchbase_mcp_server-0.5.0.dist-info/licenses/LICENSE
tools/__init__.py
tools/index.py
tools/kv.py
tools/query.py
tools/server.py
utils/__init__.py
utils/config.py
utils/connection.py
utils/constants.py
utils/context.py
iflow_mcp_couchbase_mcp_server-0.5.0.dist-info/METADATA
iflow_mcp_couchbase_mcp_server-0.5.0.dist-info/WHEEL
iflow_mcp_couchbase_mcp_server-0.5.0.dist-info/entry_points.txt
iflow_mcp_couchbase_mcp_server-0.5.0.dist-info/top_level.txt
iflow_mcp_couchbase_mcp_server-0.5.0.dist-info/RECORD
