Metadata-Version: 2.4
Name: iflow-mcp_couchbase-mcp-server
Version: 0.5.0
Summary: Couchbase MCP Server - The Developer Data Platform for Critical Applications in Our AI World
Author-email: Nithish Raghunandanan <devadvocates@couchbase.com>
License-Expression: Apache-2.0
Project-URL: Homepage, https://github.com/Couchbase-Ecosystem/mcp-server-couchbase
Project-URL: Documentation, https://github.com/Couchbase-Ecosystem/mcp-server-couchbase#readme
Project-URL: Issues, https://github.com/Couchbase-Ecosystem/mcp-server-couchbase/issues
Classifier: Development Status :: 4 - Beta
Classifier: Programming Language :: Python :: 3
Classifier: Topic :: Database
Requires-Python: >=3.10
License-File: LICENSE
Requires-Dist: click==8.2.1
Requires-Dist: couchbase==4.4.0
Requires-Dist: lark-sqlpp==0.0.1
Requires-Dist: mcp[cli]==1.12.0
Provides-Extra: dev
Requires-Dist: ruff==0.12.5; extra == "dev"
Requires-Dist: pre-commit==4.2.0; extra == "dev"
Dynamic: license-file
